pylicup/__init__.py
pylicup/__main__.py
pylicup/license_manager.py
pylicup/pylicup_logger.py
pylicup-0.3.0.dist-info/METADATA
pylicup-0.3.0.dist-info/WHEEL
pylicup-0.3.0.dist-info/RECORD
