Metadata-Version: 2.4
Name: pylicup
Version: 0.3.0
Summary: Python License Update (PyLicUp). Updates all the python headers of your project with the provided license text.
Project-URL: hoempage, https://github.com/Carsopre/PythonLicenseUpdater
Project-URL: repository, https://github.com/Carsopre/PythonLicenseUpdater
Author-email: "Carles S. Soriano Perez" <carles.sorianoperez@deltares.nl>
License-Expression: MIT
Requires-Python: <3.15,>=3.11
